{
    "airports - with unpaved runways":[
        "1",
        "1 (2013)"
    ],
    "geographic coordinates":[
        "71 00 N 8 00 W"
    ],
    "terrain":[
        "volcanic island partly covered by glaciers"
    ],
    "geography - note":[
        "barren volcanic island with some moss and grass"
    ],
    "broadcast media":[
        "a coastal radio station has been remotely operated since 1994 (2008)"
    ],
    "environment - current issues":[
        "NA"
    ],
    "legal system":[
        "the laws of Norway where applicable apply"
    ],
    "area":[
        "377 sq km",
        "377 sq km",
        "0 sq km"
    ],
    "land use":[
        "0%",
        "0%",
        "100% (2011)"
    ],
    "military - note":[
        "defense is the responsibility of Norway"
    ],
    "country name":[
        "none",
        "Jan Mayen"
    ],
    "location":[
        "Northern Europe island between the Greenland Sea and the Norwegian Sea northeast of Iceland"
    ],
    "maritime claims":[
        "4 nm",
        "10 nm",
        "200 nm",
        "200 m depth or to the depth of exploitation"
    ],
    "irrigated land":[
        "0 sq km (2011)"
    ],
    "natural hazards":[
        "dominated by the volcano Beerenberg",
        "Beerenberg (elev. 2227 m) is Norway's only active volcano; volcanic activity resumed in 1970; the most recent eruption occurred in 1985"
    ],
    "land boundaries":[
        "0 km"
    ],
    "coastline":[
        "124.1 km"
    ],
    "dependency status":[
        "territory of Norway; since August 1994 administered from Oslo through the county governor (fylkesmann) of Nordland; however authority has been delegated to a station commander of the Norwegian Defense Communication Service"
    ],
    "flag description":[
        "the flag of Norway is used"
    ],
    "area - comparative":[
        "slightly more than twice the size of Washington DC"
    ],
    "disputes - international":[
        "none"
    ],
    "population":[
        "no indigenous inhabitants",
        "personnel operate the Long Range Navigation (Loran-C) base and the weather and coastal services radio station"
    ],
    "climate":[
        "arctic maritime with frequent storms and persistent fog"
    ],
    "airports":[
        "1 (2013)"
    ],
    "natural resources":[
        "none"
    ],
    "elevation extremes":[
        "Norwegian Sea 0 m",
        "Haakon VII Toppen on Beerenberg 2277 m",
        "Beerenberg volcano has numerous peaks; the highest point on the volcano rim is named Haakon VII Toppen after Norway's first king following the reestablishment of Norwegian independence in 1905"
    ],
    "ports and terminals":[
        "none; offshore anchorage only"
    ]
}