{
    "geographic coordinates":[
        "43 44 N, 7 24 E"
    ],
    "hiv/aids - people living with hiv/aids":[
        "NA"
    ],
    "government type":[
        "constitutional monarchy"
    ],
    "religions":[
        "Roman Catholic 90% (official), other 10%"
    ],
    "unemployment rate":[
        "2% (2012)"
    ],
    "total fertility rate":[
        "1.52 children born/woman (2014 est.)"
    ],
    "national anthem":[
        "A Marcia de Muneghu (The March of Monaco)",
        "Louis NOTARI/Charles ALBRECHT",
        "music adopted 1867, lyrics adopted 1931; although French is commonly spoken, only the Monegasque lyrics are official; the French version is known as Hymne Monegasque (Monegasque Anthem); the words are generally only sung on official occasions"
    ],
    "environment - current issues":[
        "NA"
    ],
    "industries":[
        "banking, insurance, tourism, construction, small-scale industrial and consumer products"
    ],
    "legal system":[
        "civil law system influenced by French legal tradition"
    ],
    "health expenditures":[
        "4.3% of GDP (2011)"
    ],
    "urbanization":[
        "100% of total population (2011)",
        "0.04% annual rate of change (2010-15 est.)"
    ],
    "location":[
        "Western Europe, bordering the Mediterranean Sea on the southern coast of France, near the border with Italy"
    ],
    "irrigated land":[
        "NA"
    ],
    "natural hazards":[
        "NA"
    ],
    "exports":[
        "$1.115 billion (2011)",
        "$684.9 million (2010)",
        "full customs integration with France, which collects and rebates Monegasque trade duties; also participates in EU market system through customs union with France"
    ],
    "internet users":[
        "23000 (2009)"
    ],
    "heliports":[
        "1 (2012)"
    ],
    "literacy":[
        "age 15 and over can read and write",
        "99%",
        "99%",
        "99% (2003 est.)"
    ],
    "gdp - per capita (ppp)":[
        "$85500 (2011)"
    ],
    "birth rate":[
        "6.72 births/1000 population (2014 est.)"
    ],
    "internet country code":[
        ".mc"
    ],
    "suffrage":[
        "18 years of age; universal"
    ],
    "labor force":[
        "52490",
        "includes all foreign workers (2012 est.)"
    ],
    "independence":[
        "1419 (beginning of permanent rule by the House of GRIMALDI)"
    ],
    "ports and terminals":[
        "Monaco"
    ],
    "labor force - by occupation":[
        "0%",
        "16.1%",
        "83.9% (2012 est.)"
    ],
    "diplomatic representation from the us":[
        "the US does not have an embassy in Monaco; the US Ambassador to France is accredited to Monaco; the US Consul General in Marseille (France), under the authority of the US ambassador to France, handles diplomatic and consular matters concerning Monaco"
    ],
    "terrain":[
        "hilly, rugged, rocky"
    ],
    "infant mortality rate":[
        "1.81 deaths/1000 live births",
        "2.05 deaths/1000 live births",
        "1.56 deaths/1000 live births (2014 est.)"
    ],
    "geography - note":[
        "second-smallest independent state in the world (after Holy See); smallest country with a coastline; almost entirely urban"
    ],
    "political parties and leaders":[
        "Horizon Monaco [Laurent NOUVION]",
        "Renaissance [SBM (public corporation)]",
        "Union Monegasque [Stephane VALERI]"
    ],
    "broadcast media":[
        "TV Monte-Carlo (TMC) operates a TV network; cable TV available; Radio Monte-Carlo has extensive radio networks in France and Italy with French-language broadcasts to France beginning in the 1960s and Italian-language broadcasts to Italy beginning in the 1970s; other radio stations include Riviera Radio and Radio Monaco (2012)"
    ],
    "constitution":[
        "previous 1911 (suspended 1959); latest adopted 17 December 1962; amended 2002 (2013)"
    ],
    "median age":[
        "51.1 years",
        "50 years",
        "52.3 years (2014 est.)"
    ],
    "military - note":[
        "defense is the responsibility of France"
    ],
    "manpower fit for military service":[
        "4629",
        "4597 (2010 est.)"
    ],
    "country name":[
        "Principality of Monaco",
        "Monaco",
        "Principaute de Monaco",
        "Monaco"
    ],
    "capital":[
        "Monaco",
        "43 44 N, 7 25 E",
        "UTC+1 (6 hours ahead of Washington, DC, during Standard Time)",
        "+1hr, begins last Sunday in March; ends last Sunday in October"
    ],
    "gdp (purchasing power parity)":[
        "$6.213 billion (2012 est.)",
        "$5.748 billion (2011 est.)",
        "$5.47 billion (2010 est.)",
        "data are in 2012 US dollars"
    ],
    "imports - partners":[
        "Europe 70.4%, Asia 20.8%, America 4.4%, Africa 4.1% (2013 est.)"
    ],
    "drinking water source":[
        "urban: 100% of population",
        "total: 100% of population (2012 est.)"
    ],
    "debt - external":[
        "$NA"
    ],
    "coastline":[
        "4.1 km"
    ],
    "household income or consumption by percentage share":[
        "NA%",
        "NA%"
    ],
    "climate":[
        "Mediterranean with mild, wet winters and hot, dry summers"
    ],
    "hiv/aids - adult prevalence rate":[
        "NA"
    ],
    "manpower reaching militarily significant age annually":[
        "153",
        "141 (2010 est.)"
    ],
    "roadways":[
        "77 km",
        "77 km (2010)"
    ],
    "net migration rate":[
        "2.85 migrant(s)/1000 population (2014 est.)"
    ],
    "exchange rates":[
        "euros (EUR) per US dollar -",
        "0.7634 (2013 est.)",
        "0.7752 (2012 est.)",
        "0.755 (2010 est.)",
        "0.7198 (2009 est.)",
        "0.6827 (2008 est.)"
    ],
    "agriculture - products":[
        "none"
    ],
    "manpower available for military service":[
        "5749 (2010 est.)"
    ],
    "gdp - real growth rate":[
        "0.9% (2012 est.)",
        "2.5% (2010 est.)",
        "-11.5% (2009 est.)"
    ],
    "telephone system":[
        "modern automatic telephone system; the country's sole fixed line operator offers a full range of services to residential and business customers",
        "combined fixed-line and mobile-cellular teledensity exceeds 200 per 100 persons",
        "country code - 377; no satellite earth stations; connected by cable into the French communications system (2011)"
    ],
    "flag description":[
        "two equal horizontal bands of red (top) and white; the colors are those of the ruling House of Grimaldi and have been in use since 1339, making the flag one of the world's oldest national banners",
        "similar to the flag of Indonesia which is longer and the flag of Poland which is white (top) and red"
    ],
    "fiscal year":[
        "calendar year"
    ],
    "nationality":[
        "Monegasque(s) or Monacan(s)",
        "Monegasque or Monacan"
    ],
    "life expectancy at birth":[
        "89.57 years",
        "85.66 years",
        "93.64 years (2014 est.)"
    ],
    "languages":[
        "French (official), English, Italian, Monegasque"
    ],
    "area":[
        "2 sq km",
        "2 sq km",
        "0 sq km"
    ],
    "natural resources":[
        "none"
    ],
    "maritime claims":[
        "12 nm",
        "12 nm"
    ],
    "exports - partners":[
        "Europe 73.2%, Africa 14.6%, America 5.2%, Asia 4.9% (2013 est.)"
    ],
    "population growth rate":[
        "0.06% (2014 est.)"
    ],
    "sanitation facility access":[
        "urban: 100% of population",
        "total: 100% of population",
        "",
        "urban: 0% of population",
        "total: 0% of population (2012 est.)"
    ],
    "gdp - composition, by sector of origin":[
        "0%",
        "10%",
        "90% (2011)"
    ],
    "age structure":[
        "11.7% (male 1828/female 1742)",
        "9.2% (male 1445/female 1371)",
        "35.1% (male 5332/female 5363)",
        "14.5% (male 2223/female 2203)",
        "28.7% (male 4020/female 4981) (2014 est.)"
    ],
    "internet hosts":[
        "26009 (2012)"
    ],
    "land boundaries":[
        "6 km",
        "France 6 km"
    ],
    "area - comparative":[
        "about three times the size of The Mall in Washington, DC"
    ],
    "disputes - international":[
        "none"
    ],
    "population":[
        "30508",
        "immigrants make up more than 60% of the total population, according to UN data (2013) (July 2014 est.)"
    ],
    "national holiday":[
        "National Day (Saint Rainier's Day), 19 November (1857)"
    ],
    "budget surplus (+) or deficit (-)":[
        "-1.2% of GDP (2011 est.)"
    ],
    "budget":[
        "$1.044 billion",
        "$1.111 billion (2011 est.)"
    ],
    "population below poverty line":[
        "NA%"
    ],
    "sex ratio":[
        "1.04 male(s)/female",
        "1.05 male(s)/female",
        "1.05 male(s)/female",
        "0.99 male(s)/female",
        "0.95 male(s)/female",
        "0.81 male(s)/female",
        "0.95 male(s)/female (2014 est.)"
    ],
    "death rate":[
        "9.01 deaths/1000 population (2014 est.)"
    ],
    "market value of publicly traded shares":[
        "$NA"
    ],
    "industrial production growth rate":[
        "NA%"
    ],
    "inflation rate (consumer prices)":[
        "1.5% (2010)"
    ],
    "diplomatic representation in the us":[
        "Ambassador Maguy MACCARIO-DOYLE (since 3 December 2013)",
        "3400 International Drive NW, Suite 2K-100, Washington, DC 20008",
        "(202) 234-1530",
        "(202) 244-7656",
        "New York"
    ],
    "imports":[
        "$1.162 billion (2011)",
        "$850.2 million (2010)",
        "full customs integration with France, which collects and rebates Monegasque trade duties; also participates in EU market system through customs union with France"
    ],
    "education expenditures":[
        "1.6% of GDP (2011)"
    ],
    "hospital bed density":[
        "16.5 beds/1000 population (2011)"
    ],
    "ethnic groups":[
        "French 47%, Monegasque 16%, Italian 16%, other 21%"
    ],
    "unemployment, youth ages 15-24":[
        "6.9%",
        "6.6%",
        "7.4% (2000)"
    ],
    "land use":[
        "0%",
        "1%",
        "99% (urban area) (2011)"
    ],
    "taxes and other revenues":[
        "18.2% of GDP (2011 est.)"
    ],
    "political pressure groups and leaders":[
        "NA"
    ],
    "administrative divisions":[
        "none; there are no first-order administrative divisions as defined by the US Government, but there are four quarters (quartiers, singular - quartier); Fontvieille, La Condamine, Monaco-Ville, Monte-Carlo; note - Moneghetti, a part of La Condamine, is sometimes called the 5th quarter of Monaco"
    ],
    "hiv/aids - deaths":[
        "NA"
    ],
    "telephones - mobile cellular":[
        "33200 (2012)"
    ],
    "international law organization participation":[
        "has not submitted an ICJ jurisdiction declaration; non-party state to the ICCt"
    ],
    "elevation extremes":[
        "Mediterranean Sea 0 m",
        "Mont Agel 140 m"
    ],
    "telephones - main lines in use":[
        "44500 (2012)"
    ],
    "physicians density":[
        "7.06 physicians/1000 population (2011)"
    ],
    "international organization participation":[
        "CD, CE, FAO, IAEA, ICAO, ICC (national committees), ICRM, IFRCS, IHO, IMO, IMSO, Interpol, IOC, IPU, ITSO, ITU, OAS (observer), OIF, OPCW, OSCE, Schengen Convention (de facto member), UN, UNCTAD, UNESCO, UNIDO, Union Latina, UNWTO, UPU, WHO, WIPO, WMO"
    ],
    "gdp (official exchange rate)":[
        "$5.748 billion (2011 est.)"
    ]
}